bitblas
