Metadata-Version: 2.1
Name: bitblas
Version: 0.0.1.dev13
Summary: A light weight framework to generate high performance CUDA/HIP code for BLAS operators.
Home-page: https://github.com/microsoft/BitBLAS
Author: Microsoft Research
License: MIT
Keywords: BLAS,CUDA,HIP,Code Generation,TVM
Platform: Environment :: GPU :: NVIDIA CUDA
Platform: Operating System :: POSIX :: Linux
Classifier: Programming Language :: Python :: 3.8
Classifier: License :: OSI Approved :: MIT License
Classifier: Operating System :: OS Independent
Classifier: Intended Audience :: Developers
Classifier: Intended Audience :: Science/Research
Requires-Python: >=3.8
License-File: LICENSE
Requires-Dist: cffi
Requires-Dist: cpplint
Requires-Dist: Cython
Requires-Dist: decorator
Requires-Dist: docutils
Requires-Dist: dtlib
Requires-Dist: numpy >=1.23.5
Requires-Dist: pytest >=6.2.4
Requires-Dist: pytest-xdist >=2.2.1
Requires-Dist: packaging >=21.0
Requires-Dist: PyYAML
Requires-Dist: tqdm >=4.62.3
Requires-Dist: typing-extensions >=4.10.0
Requires-Dist: requests
Requires-Dist: attrs
Requires-Dist: cloudpickle
Requires-Dist: ml-dtypes
Requires-Dist: psutil
Requires-Dist: scipy
Requires-Dist: tornado
Requires-Dist: torch
Requires-Dist: thefuzz
Requires-Dist: tabulate
